micropg_lite.py
micropg_lite-3.1.1.dist-info/METADATA
micropg_lite-3.1.1.dist-info/WHEEL
micropg_lite-3.1.1.dist-info/top_level.txt
micropg_lite-3.1.1.dist-info/RECORD
