Metadata-Version: 2.1
Name: micropg_lite
Version: 3.1.1
Summary: A lightweight PostgreSQL database driver for MicroPython, designed for microcontrollers (e.g., ESP8266) with limited RAM.
Home-page: https://github.com/TimonW-Dev/micropg_lite
Author: TimonW-Dev
Author-email: timon-github@outlook.com
Project-URL: Bug Tracker, https://github.com/TimonW-Dev/micropg_lite/issues
Project-URL: Documentation, https://github.com/TimonW-Dev/micropg_lite/wiki
Project-URL: Source Code, https://github.com/TimonW-Dev/micropg_lite
Keywords: micropython postgresql esp8266 database
Classifier: Programming Language :: Python :: Implementation :: MicroPython
Classifier: Programming Language :: Python :: 3
Classifier: License :: OSI Approved :: MIT License
Classifier: Operating System :: Other OS
Classifier: Topic :: Software Development :: Embedded Systems
Classifier: Topic :: Database
Requires-Python: >=3.4
